LICENSE
README.md
setup.py
bin/lqc
lqc/__init__.py
lqc/cs.py
lqc/indel.py
lqc/mismatch.py
lqc/readstat.py
lqc/report_figure.py
lqc/report_html.py
lqc/report_table.py
lqc/splice.py
lqc/stat.py
lqc/utils.py
lqc.egg-info/PKG-INFO
lqc.egg-info/SOURCES.txt
lqc.egg-info/dependency_links.txt
lqc.egg-info/not-zip-safe
lqc.egg-info/requires.txt
lqc.egg-info/top_level.txt
lqc/template/__init__.py
lqc/template/card.svg
lqc/template/logo_pink.svg
lqc/template/logo_white.svg
lqc/template/template.html
lqc/test/__init__.py
lqc/test/cs_test.test_data
lqc/test/generate_cs_test_data.py
lqc/test/test_cs.py