Metadata-Version: 2.1
Name: lqc
Version: 0.0.5
Summary: The Long-read RNA-seq quality control software.
Home-page: https://github.com/xiaolab/LQC
Author: Zhiheng Liu
Author-email: wolfsonliu@live.com
License: GPL
Platform: UNKNOWN
Classifier: Programming Language :: Python :: 3
Classifier: License :: OSI Approved :: GNU General Public License v3 or later (GPLv3+)
Classifier: Operating System :: OS Independent
Classifier: Topic :: Scientific/Engineering :: Bio-Informatics
Requires-Python: >=3.7
License-File: LICENSE
